Workbook

Sheet 消耗品一覧
A1: No. | B1: メーカー | C1: 機種（台帳の型番） | D1: 台数 | E1: 区分 | F1: 色 | G1: 商品名 | H1: 品番・型番 | I1: 品種コード | J1: 印刷可能枚数 | K1: 参考価格 | L1: 価格の別 | M1: リサイクル/互換 | N1: 照合キー | O1: 台帳マスタ | P1: 備考 | Q1: 出典
A2: 1 | B2: Brother | C2: Brother HL-L3230CDW | D2: 1 | E2: トナー | F2: ブラック | G2: トナーカートリッジ TN-293BK | H2: TN-293BK | J2: 3000 | K2: 11770 | L2: 直販価格（税込） | M2: あり | N2: TN-293BK | O2: =IF($N2="","—",IF(COUNTIF(台帳マスタ!$A:$A,$N2)>0,"登録あり","未登録")) | Q2: S15
A3: 2 | B3: Brother | C3: Brother HL-L3230CDW | D3: 1 | E3: トナー | F3: シアン | G3: トナーカートリッジ TN-293C | H3: TN-293C | J3: 1300 | K3: 9900 | L3: 直販価格（税込） | M3: あり | N3: TN-293C | O3: =IF($N3="","—",IF(COUNTIF(台帳マスタ!$A:$A,$N3)>0,"登録あり","未登録")) | Q3: S15
A4: 3 | B4: Brother | C4: Brother HL-L3230CDW | D4: 1 | E4: トナー | F4: マゼンタ | G4: トナーカートリッジ TN-293M | H4: TN-293M | J4: 1300 | K4: 9900 | L4: 直販価格（税込） | M4: あり | N4: TN-293M | O4: =IF($N4="","—",IF(COUNTIF(台帳マスタ!$A:$A,$N4)>0,"登録あり","未登録")) | Q4: S15
A5: 4 | B5: Brother | C5: Brother HL-L3230CDW | D5: 1 | E5: トナー | F5: イエロー | G5: トナーカートリッジ TN-293Y | H5: TN-293Y | J5: 1300 | K5: 9900 | L5: 直販価格（税込） | M5: あり | N5: TN-293Y | O5: =IF($N5="","—",IF(COUNTIF(台帳マスタ!$A:$A,$N5)>0,"登録あり","未登録")) | Q5: S15
A6: 5 | B6: Brother | C6: Brother HL-L3230CDW | D6: 1 | E6: トナー | F6: シアン | G6: 大容量トナーカートリッジ TN-297C | H6: TN-297C | J6: 2300 | L6: 直販価格（税込） | M6: あり | N6: TN-297C | O6: =IF($N6="","—",IF(COUNTIF(台帳マスタ!$A:$A,$N6)>0,"登録あり","未登録")) | P6: 黒の大容量は設定なし | Q6: S14
A7: 6 | B7: Brother | C7: Brother HL-L3230CDW | D7: 1 | E7: トナー | F7: マゼンタ | G7: 大容量トナーカートリッジ TN-297M | H7: TN-297M | J7: 2300 | L7: 直販価格（税込） | M7: あり | N7: TN-297M | O7: =IF($N7="","—",IF(COUNTIF(台帳マスタ!$A:$A,$N7)>0,"登録あり","未登録")) | P7: 黒の大容量は設定なし | Q7: S14
A8: 7 | B8: Brother | C8: Brother HL-L3230CDW | D8: 1 | E8: トナー | F8: イエロー | G8: 大容量トナーカートリッジ TN-297Y | H8: TN-297Y | J8: 2300 | L8: 直販価格（税込） | M8: あり | N8: TN-297Y | O8: =IF($N8="","—",IF(COUNTIF(台帳マスタ!$A:$A,$N8)>0,"登録あり","未登録")) | P8: 黒の大容量は設定なし | Q8: S14
A9: 8 | B9: Brother | C9: Brother HL-L3230CDW | D9: 1 | E9: ドラム | F9: ブラック | G9: ドラムユニット DR-293CL-BK | H9: DR-293CL-BK | J9: 18000 | K9: 6160 | L9: 直販価格（税込） | M9: あり | N9: DR-293CL-BK | O9: =IF($N9="","—",IF(COUNTIF(台帳マスタ!$A:$A,$N9)>0,"登録あり","未登録")) | Q9: S15
A10: 9 | B10: Brother | C10: Brother HL-L3230CDW | D10: 1 | E10: ドラム | F10: カラー | G10: ドラムユニット DR-293CL-CMY（カラー3本） | H10: DR-293CL-CMY | J10: 18000 | K10: 6160 | L10: 直販価格（税込） | M10: あり | N10: DR-293CL-CMY | O10: =IF($N10="","—",IF(COUNTIF(台帳マスタ!$A:$A,$N10)>0,"登録あり","未登録")) | P10: 台帳は色別（-C/-M/-Y）で登録。純正はCMY3本セット | Q10: S15
A11: 10 | B11: Brother | C11: Brother HL-L3230CDW | D11: 1 | E11: ドラム | F11: BK,C,M,Y | G11: ドラムユニット DR-293CL（4本入り） | H11: DR-293CL | J11: 18000 | K11: 16610 | L11: 直販価格（税込） | M11: あり | N11: DR-293CL | O11: =IF($N11="","—",IF(COUNTIF(台帳マスタ!$A:$A,$N11)>0,"登録あり","未登録")) | Q11: S15
A12: 11 | B12: Brother | C12: Brother HL-L3230CDW | D12: 1 | E12: ベルト | F12: — | G12: ベルトユニット BU-223CL | H12: BU-223CL | J12: 50000 | K12: 27500 | L12: 直販価格（税込） | M12: あり | N12: BU-223CL | O12: =IF($N12="","—",IF(COUNTIF(台帳マスタ!$A:$A,$N12)>0,"登録あり","未登録")) | P12: 定期交換部品。台帳マスタに未登録 | Q12: S15
A13: 12 | B13: Brother | C13: Brother HL-L3230CDW | D13: 1 | E13: 廃トナー | F13: — | G13: 廃トナーボックス WT-223CL | H13: WT-223CL | J13: 50000 | K13: 3080 | L13: 直販価格（税込） | M13: あり | N13: WT-223CL | O13: =IF($N13="","—",IF(COUNTIF(台帳マスタ!$A:$A,$N13)>0,"登録あり","未登録")) | P13: 定期交換部品。台帳マスタに未登録 | Q13: S15
A14: 13 | B14: Canon | C14: Canon iR-ADV C3520F | D14: 10 | E14: トナー | F14: ブラック | G14: トナーカートリッジ NPG-67 ブラック | H14: NPG-67 BK | J14: 15000 | K14: 17600 | L14: 実売の参考（税込） | M14: あり | N14: NPG-67BK | O14: =IF($N14="","—",IF(COUNTIF(台帳マスタ!$A:$A,$N14)>0,"登録あり","未登録")) | P14: 純正。価格は販売店により幅がある | Q14: S20
A15: 14 | B15: Canon | C15: Canon iR-ADV C3520F | D15: 10 | E15: トナー | F15: シアン | G15: トナーカートリッジ NPG-67 シアン | H15: NPG-67 C | J15: 9000 | K15: 17600 | L15: 実売の参考（税込） | M15: あり | N15: NPG-67 C | O15: =IF($N15="","—",IF(COUNTIF(台帳マスタ!$A:$A,$N15)>0,"登録あり","未登録")) | P15: 純正。4色セットの例 54,180 円（税別） | Q15: S20
A16: 15 | B16: Canon | C16: Canon iR-ADV C3520F | D16: 10 | E16: トナー | F16: マゼンタ | G16: トナーカートリッジ NPG-67 マゼンタ | H16: NPG-67 M | J16: 9000 | K16: 17600 | L16: 実売の参考（税込） | M16: あり | N16: NPG-67 M | O16: =IF($N16="","—",IF(COUNTIF(台帳マスタ!$A:$A,$N16)>0,"登録あり","未登録")) | P16: 純正。4色セットの例 54,180 円（税別） | Q16: S20
A17: 16 | B17: Canon | C17: Canon iR-ADV C3520F | D17: 10 | E17: トナー | F17: イエロー | G17: トナーカートリッジ NPG-67 イエロー | H17: NPG-67 Y | J17: 9000 | K17: 17600 | L17: 実売の参考（税込） | M17: あり | N17: NPG-67 Y | O17: =IF($N17="","—",IF(COUNTIF(台帳マスタ!$A:$A,$N17)>0,"登録あり","未登録")) | P17: 純正。4色セットの例 54,180 円（税別） | Q17: S20
A18: 17 | B18: Canon | C18: Canon iR-ADV C3520F | D18: 10 | E18: 廃トナー | F18: — | G18: 回収トナー容器 WT-202 | H18: WT-202 | J18: 100000 | K18: 8800 | L18: 実売の参考（税込） | M18: あり | N18: WT-202 | O18: =IF($N18="","—",IF(COUNTIF(台帳マスタ!$A:$A,$N18)>0,"登録あり","未登録")) | P18: 約10万枚で交換。7,700〜9,780 円の実売例 | Q18: S21
A19: 18 | B19: Canon | C19: Canon iR-ADV C3520F | D19: 10 | E19: ドラム | F19: 各色共通 | G19: ドラムユニット NPG-67（海外名 GPR-53） | H19: NPG-67 ドラム | J19: 72600 | L19: 実売の参考（税込） | M19: あり | N19: NPG-67 ドラム | O19: =IF($N19="","—",IF(COUNTIF(台帳マスタ!$A:$A,$N19)>0,"登録あり","未登録")) | P19: 国内は保守契約でのサービス交換が基本。輸入純正が流通 | Q19: S22
A20: 19 | B20: Canon | C20: Canon iR-ADV C3530F | D20: 4 | E20: トナー | F20: ブラック | G20: トナーカートリッジ NPG-67 ブラック | H20: NPG-67 BK | J20: 15000 | K20: 17600 | L20: 実売の参考（税込） | M20: あり | N20: NPG-67BK | O20: =IF($N20="","—",IF(COUNTIF(台帳マスタ!$A:$A,$N20)>0,"登録あり","未登録")) | P20: 純正。価格は販売店により幅がある | Q20: S20
A21: 20 | B21: Canon | C21: Canon iR-ADV C3530F | D21: 4 | E21: トナー | F21: シアン | G21: トナーカートリッジ NPG-67 シアン | H21: NPG-67 C | J21: 9000 | K21: 17600 | L21: 実売の参考（税込） | M21: あり | N21: NPG-67 C | O21: =IF($N21="","—",IF(COUNTIF(台帳マスタ!$A:$A,$N21)>0,"登録あり","未登録")) | P21: 純正。4色セットの例 54,180 円（税別） | Q21: S20
A22: 21 | B22: Canon | C22: Canon iR-ADV C3530F | D22: 4 | E22: トナー | F22: マゼンタ | G22: トナーカートリッジ NPG-67 マゼンタ | H22: NPG-67 M | J22: 9000 | K22: 17600 | L22: 実売の参考（税込） | M22: あり | N22: NPG-67 M | O22: =IF($N22="","—",IF(COUNTIF(台帳マスタ!$A:$A,$N22)>0,"登録あり","未登録")) | P22: 純正。4色セットの例 54,180 円（税別） | Q22: S20
A23: 22 | B23: Canon | C23: Canon iR-ADV C3530F | D23: 4 | E23: トナー | F23: イエロー | G23: トナーカートリッジ NPG-67 イエロー | H23: NPG-67 Y | J23: 9000 | K23: 17600 | L23: 実売の参考（税込） | M23: あり | N23: NPG-67 Y | O23: =IF($N23="","—",IF(COUNTIF(台帳マスタ!$A:$A,$N23)>0,"登録あり","未登録")) | P23: 純正。4色セットの例 54,180 円（税別） | Q23: S20
A24: 23 | B24: Canon | C24: Canon iR-ADV C3530F | D24: 4 | E24: 廃トナー | F24: — | G24: 回収トナー容器 WT-202 | H24: WT-202 | J24: 100000 | K24: 8800 | L24: 実売の参考（税込） | M24: あり | N24: WT-202 | O24: =IF($N24="","—",IF(COUNTIF(台帳マスタ!$A:$A,$N24)>0,"登録あり","未登録")) | P24: 約10万枚で交換。7,700〜9,780 円の実売例 | Q24: S21
A25: 24 | B25: Canon | C25: Canon iR-ADV C3530F | D25: 4 | E25: ドラム | F25: 各色共通 | G25: ドラムユニット NPG-67（海外名 GPR-53） | H25: NPG-67 ドラム | J25: 72600 | L25: 実売の参考（税込） | M25: あり | N25: NPG-67 ドラム | O25: =IF($N25="","—",IF(COUNTIF(台帳マスタ!$A:$A,$N25)>0,"登録あり","未登録")) | P25: 国内は保守契約でのサービス交換が基本。輸入純正が流通 | Q25: S22
A26: 25 | B26: Canon | C26: Canon LBP-6710 | D26: 1 | E26: トナー | F26: ブラック | G26: トナーカートリッジ524 | H26: CRG-524 | I26: 3481B004 | J26: 6000 | L26: 直販価格（税込） | M26: あり | N26: カートリッジ524 | O26: =IF($N26="","—",IF(COUNTIF(台帳マスタ!$A:$A,$N26)>0,"登録あり","未登録")) | P26: ドラム一体型 | Q26: S17
A27: 26 | B27: Canon | C27: Canon LBP-6710 | D27: 1 | E27: トナー | F27: ブラック | G27: トナーカートリッジ524II（大容量） | H27: CRG-524II | I27: 3482B004 | J27: 12500 | K27: 52800 | L27: 直販価格（税込） | M27: あり | N27: CRG-524II | O27: =IF($N27="","—",IF(COUNTIF(台帳マスタ!$A:$A,$N27)>0,"登録あり","未登録")) | P27: ドラム一体型。キヤノンオンラインショップ価格 | Q27: S18
A28: 27 | B28: Canon | C28: Canon LBP-6710 | D28: 1 | E28: ドラム | F28: — | G28: （別売の感光体なし・カートリッジ一体型） | H28: — | L28: — | M28: あり | O28: =IF($N28="","—",IF(COUNTIF(台帳マスタ!$A:$A,$N28)>0,"登録あり","未登録")) | P28: この機種はドラム別売なし | Q28: S17
A29: 28 | B29: EPSON | C29: EPSON PX-M791FT | D29: 3 | E29: インク | F29: ブラック | G29: インクボトル IT08KA（127ml） | H29: IT08KA | J29: 7500 | L29: オープン価格 | M29: あり（互換） | N29: IT08KA | O29: =IF($N29="","—",IF(COUNTIF(台帳マスタ!$A:$A,$N29)>0,"登録あり","未登録")) | Q29: S12
A30: 29 | B30: EPSON | C30: EPSON PX-M791FT | D30: 3 | E30: インク | F30: シアン | G30: インクボトル IT08CA（70ml） | H30: IT08CA | J30: 6000 | L30: オープン価格 | M30: あり（互換） | N30: IT08CA | O30: =IF($N30="","—",IF(COUNTIF(台帳マスタ!$A:$A,$N30)>0,"登録あり","未登録")) | Q30: S12
A31: 30 | B31: EPSON | C31: EPSON PX-M791FT | D31: 3 | E31: インク | F31: マゼンタ | G31: インクボトル IT08MA（70ml） | H31: IT08MA | J31: 6000 | L31: オープン価格 | M31: あり（互換） | N31: IT08MA | O31: =IF($N31="","—",IF(COUNTIF(台帳マスタ!$A:$A,$N31)>0,"登録あり","未登録")) | Q31: S12
A32: 31 | B32: EPSON | C32: EPSON PX-M791FT | D32: 3 | E32: インク | F32: イエロー | G32: インクボトル IT08YA（70ml） | H32: IT08YA | J32: 6000 | L32: オープン価格 | M32: あり（互換） | N32: IT08YA | O32: =IF($N32="","—",IF(COUNTIF(台帳マスタ!$A:$A,$N32)>0,"登録あり","未登録")) | Q32: S12
A33: 32 | B33: EPSON | C33: EPSON PX-M791FT | D33: 3 | E33: メンテナンス | F33: — | G33: メンテナンスボックス PXMB9 | H33: PXMB9 | L33: オープン価格 | M33: あり（互換） | N33: PXMB9 | O33: =IF($N33="","—",IF(COUNTIF(台帳マスタ!$A:$A,$N33)>0,"登録あり","未登録")) | P33: 廃インク吸収体 | Q33: S12
A34: 33 | B34: EPSON | C34: EPSON PX-S381 | D34: 1 | E34: インク | F34: ブラック | G34: インクパック IP04KA（795ml） | H34: IP04KA | J34: 40000 | L34: オープン価格 | M34: あり（互換） | N34: IP04KA | O34: =IF($N34="","—",IF(COUNTIF(台帳マスタ!$A:$A,$N34)>0,"登録あり","未登録")) | P34: PX-M381FL/PX-S381L 用 | Q34: S13
A35: 34 | B35: EPSON | C35: EPSON PX-S381 | D35: 1 | E35: インク | F35: ブラック | G35: インクパック IP03KB（旧型・使用可） | H35: IP03KB | L35: オープン価格 | M35: あり（互換） | N35: IP03KB | O35: =IF($N35="","—",IF(COUNTIF(台帳マスタ!$A:$A,$N35)>0,"登録あり","未登録")) | P35: 旧機種用だが引き続き使用可 | Q35: S13
A36: 35 | B36: EPSON | C36: EPSON PX-S381 | D36: 1 | E36: メンテナンス | F36: — | G36: メンテナンスボックス PXMB8 | H36: PXMB8 | L36: オープン価格 | M36: あり（互換） | N36: PXMB8 | O36: =IF($N36="","—",IF(COUNTIF(台帳マスタ!$A:$A,$N36)>0,"登録あり","未登録")) | Q36: S13
A37: 36 | B37: EPSON | C37: EPSON PX-S381L | D37: 4 | E37: インク | F37: ブラック | G37: インクパック IP04KA（795ml） | H37: IP04KA | J37: 40000 | L37: オープン価格 | M37: あり（互換） | N37: IP04KA | O37: =IF($N37="","—",IF(COUNTIF(台帳マスタ!$A:$A,$N37)>0,"登録あり","未登録")) | P37: PX-M381FL/PX-S381L 用 | Q37: S13
A38: 37 | B38: EPSON | C38: EPSON PX-S381L | D38: 4 | E38: インク | F38: ブラック | G38: インクパック IP03KB（旧型・使用可） | H38: IP03KB | L38: オープン価格 | M38: あり（互換） | N38: IP03KB | O38: =IF($N38="","—",IF(COUNTIF(台帳マスタ!$A:$A,$N38)>0,"登録あり","未登録")) | P38: 旧機種用だが引き続き使用可 | Q38: S13
A39: 38 | B39: EPSON | C39: EPSON PX-S381L | D39: 4 | E39: メンテナンス | F39: — | G39: メンテナンスボックス PXMB8 | H39: PXMB8 | L39: オープン価格 | M39: あり（互換） | N39: PXMB8 | O39: =IF($N39="","—",IF(COUNTIF(台帳マスタ!$A:$A,$N39)>0,"登録あり","未登録")) | Q39: S13
A40: 39 | B40: FUJITSU | C40: FUJITSU XL-9322 | D40: 1 | E40: トナー | F40: ブラック | G40: トナーカートリッジ LB321A（標準） | H40: LB321A | J40: 6000 | K40: 35970 | L40: 実売の参考（税込） | M40: あり | N40: LB321A | O40: =IF($N40="","—",IF(COUNTIF(台帳マスタ!$A:$A,$N40)>0,"登録あり","未登録")) | P40: メーカー希望小売価格 | Q40: S23
A41: 40 | B41: FUJITSU | C41: FUJITSU XL-9322 | D41: 1 | E41: トナー | F41: ブラック | G41: トナーカートリッジ LB321M（大容量） | H41: LB321M | J41: 10000 | K41: 46750 | L41: 実売の参考（税込） | M41: あり | N41: LB321B | O41: =IF($N41="","—",IF(COUNTIF(台帳マスタ!$A:$A,$N41)>0,"登録あり","未登録")) | P41: 資料により LB321B 表記もあり。要確認 | Q41: S23
A42: 41 | B42: FUJITSU | C42: FUJITSU XL-9322 | D42: 1 | E42: ドラム | F42: — | G42: ドラムカートリッジ LB321 | H42: LB321 | I42: 899230 | J42: 25000 | K42: 15180 | L42: 実売の参考（税込） | M42: あり | N42: LB321 | O42: =IF($N42="","—",IF(COUNTIF(台帳マスタ!$A:$A,$N42)>0,"登録あり","未登録")) | P42: 連続印刷時。1ページ/ジョブでは約14,300枚 | Q42: S23
A43: 42 | B43: FujiXerox | C43: FujiXerox DocuPrint CP500 d | D43: 1 | E43: トナー | F43: ブラック | G43: トナーカートリッジ ブラック | H43: CT203053 | I43: CT203053 | J43: 7000 | K43: 24300 | L43: メーカー標準価格（税別） | M43: あり | N43: CT203053 | O43: =IF($N43="","—",IF(COUNTIF(台帳マスタ!$A:$A,$N43)>0,"登録あり","未登録")) | P43: 標準容量 | Q43: S11
A44: 43 | B44: FujiXerox | C44: FujiXerox DocuPrint CP500 d | D44: 1 | E44: トナー | F44: シアン | G44: トナーカートリッジ シアン | H44: CT203054 | I44: CT203054 | J44: 5000 | K44: 18500 | L44: メーカー標準価格（税別） | M44: あり | N44: CT203054 | O44: =IF($N44="","—",IF(COUNTIF(台帳マスタ!$A:$A,$N44)>0,"登録あり","未登録")) | P44: 標準容量 | Q44: S11
A45: 44 | B45: FujiXerox | C45: FujiXerox DocuPrint CP500 d | D45: 1 | E45: トナー | F45: マゼンタ | G45: トナーカートリッジ マゼンタ | H45: CT203055 | I45: CT203055 | J45: 5000 | K45: 18500 | L45: メーカー標準価格（税別） | M45: あり | N45: CT203055 | O45: =IF($N45="","—",IF(COUNTIF(台帳マスタ!$A:$A,$N45)>0,"登録あり","未登録")) | P45: 標準容量 | Q45: S11
A46: 45 | B46: FujiXerox | C46: FujiXerox DocuPrint CP500 d | D46: 1 | E46: トナー | F46: イエロー | G46: トナーカートリッジ イエロー | H46: CT203056 | I46: CT203056 | J46: 5000 | K46: 18500 | L46: メーカー標準価格（税別） | M46: あり | N46: CT203056 | O46: =IF($N46="","—",IF(COUNTIF(台帳マスタ!$A:$A,$N46)>0,"登録あり","未登録")) | P46: 標準容量 | Q46: S11
A47: 46 | B47: FujiXerox | C47: FujiXerox DocuPrint CP500 d | D47: 1 | E47: トナー | F47: ブラック | G47: 大容量トナーカートリッジ ブラック | H47: CT203057 | I47: CT203057 | J47: 15000 | K47: 46200 | L47: メーカー標準価格（税別） | M47: あり | N47: CT203057 | O47: =IF($N47="","—",IF(COUNTIF(台帳マスタ!$A:$A,$N47)>0,"登録あり","未登録")) | P47: 大容量 | Q47: S11
A48: 47 | B48: FujiXerox | C48: FujiXerox DocuPrint CP500 d | D48: 1 | E48: トナー | F48: シアン | G48: 大容量トナーカートリッジ シアン | H48: CT203058 | I48: CT203058 | J48: 11000 | K48: 37000 | L48: メーカー標準価格（税別） | M48: あり | N48: CT203058 | O48: =IF($N48="","—",IF(COUNTIF(台帳マスタ!$A:$A,$N48)>0,"登録あり","未登録")) | P48: 大容量 | Q48: S11
A49: 48 | B49: FujiXerox | C49: FujiXerox DocuPrint CP500 d | D49: 1 | E49: トナー | F49: マゼンタ | G49: 大容量トナーカートリッジ マゼンタ | H49: CT203059 | I49: CT203059 | J49: 11000 | K49: 37000 | L49: メーカー標準価格（税別） | M49: あり | N49: CT203059 | O49: =IF($N49="","—",IF(COUNTIF(台帳マスタ!$A:$A,$N49)>0,"登録あり","未登録")) | P49: 大容量 | Q49: S11
A50: 49 | B50: FujiXerox | C50: FujiXerox DocuPrint CP500 d | D50: 1 | E50: トナー | F50: イエロー | G50: 大容量トナーカートリッジ イエロー | H50: CT203060 | I50: CT203060 | J50: 11000 | K50: 37000 | L50: メーカー標準価格（税別） | M50: あり | N50: CT203060 | O50: =IF($N50="","—",IF(COUNTIF(台帳マスタ!$A:$A,$N50)>0,"登録あり","未登録")) | P50: 大容量 | Q50: S11
A51: 50 | B51: FujiXerox | C51: FujiXerox DocuPrint CP500 d | D51: 1 | E51: ドラム | F51: ブラック | G51: ドラムカートリッジ ブラック | H51: CT351149 | I51: CT351149 | J51: 40000 | K51: 14300 | L51: メーカー標準価格（税別） | M51: あり | N51: CT351149 | O51: =IF($N51="","—",IF(COUNTIF(台帳マスタ!$A:$A,$N51)>0,"登録あり","未登録")) | Q51: S11
A52: 51 | B52: FujiXerox | C52: FujiXerox DocuPrint CP500 d | D52: 1 | E52: ドラム | F52: シアン | G52: ドラムカートリッジ シアン | H52: CT351150 | I52: CT351150 | J52: 40000 | K52: 14300 | L52: メーカー標準価格（税別） | M52: あり | N52: CT351150 | O52: =IF($N52="","—",IF(COUNTIF(台帳マスタ!$A:$A,$N52)>0,"登録あり","未登録")) | Q52: S11
A53: 52 | B53: FujiXerox | C53: FujiXerox DocuPrint CP500 d | D53: 1 | E53: ドラム | F53: マゼンタ | G53: ドラムカートリッジ マゼンタ | H53: CT351151 | I53: CT351151 | J53: 40000 | K53: 14300 | L53: メーカー標準価格（税別） | M53: あり | N53: CT351151 | O53: =IF($N53="","—",IF(COUNTIF(台帳マスタ!$A:$A,$N53)>0,"登録あり","未登録")) | Q53: S11
A54: 53 | B54: FujiXerox | C54: FujiXerox DocuPrint CP500 d | D54: 1 | E54: ドラム | F54: イエロー | G54: ドラムカートリッジ イエロー | H54: CT351152 | I54: CT351152 | J54: 40000 | K54: 14300 | L54: メーカー標準価格（税別） | M54: あり | N54: CT351152 | O54: =IF($N54="","—",IF(COUNTIF(台帳マスタ!$A:$A,$N54)>0,"登録あり","未登録")) | Q54: S11
A55: 54 | B55: FujiXerox | C55: FujiXerox DocuPrint CP500 d | D55: 1 | E55: 廃トナー | F55: — | G55: トナー回収ボトル | H55: CWAA0915 | I55: CWAA0915 | J55: 30000 | K55: 3500 | L55: メーカー標準価格（税別） | M55: あり | N55: CWAA0915 | O55: =IF($N55="","—",IF(COUNTIF(台帳マスタ!$A:$A,$N55)>0,"登録あり","未登録")) | Q55: S11
A56: 55 | B56: HP | C56: HP LaserJet M601 | D56: 1 | E56: トナー | F56: ブラック | G56: HP 90A 黒トナーカートリッジ | H56: CE390A | J56: 10000 | L56: — | M56: あり | N56: CE390A | O56: =IF($N56="","—",IF(COUNTIF(台帳マスタ!$A:$A,$N56)>0,"登録あり","未登録")) | Q56: S25
A57: 56 | B57: HP | C57: HP LaserJet M601 | D57: 1 | E57: トナー | F57: ブラック | G57: HP 90X 黒トナーカートリッジ（大容量） | H57: CE390X | J57: 24000 | L57: — | M57: あり | N57: CE390X | O57: =IF($N57="","—",IF(COUNTIF(台帳マスタ!$A:$A,$N57)>0,"登録あり","未登録")) | Q57: S25
A58: 57 | B58: HP | C58: HP LaserJet M601 | D58: 1 | E58: メンテナンス | F58: — | G58: メンテナンスキット（定着器・ローラー類） | H58: CF064A | J58: 225000 | L58: — | M58: あり | N58: CF064A | O58: =IF($N58="","—",IF(COUNTIF(台帳マスタ!$A:$A,$N58)>0,"登録あり","未登録")) | P58: 純正保守部品 | Q58: S25
A59: 58 | B59: KYOCERA | C59: KYOCERA ECOSYS PA6000x | D59: 3 | E59: トナー | F59: ブラック | G59: トナーキット TK-3431（2本単位） | H59: TK-3431 | J59: 25000 | K59: 40000 | L59: メーカー標準価格（税別） | M59: あり（リターン方式） | N59: TK-3431 | O59: =IF($N59="","—",IF(COUNTIF(台帳マスタ!$A:$A,$N59)>0,"登録あり","未登録")) | P59: 2本で 40,000 円（税別） | Q59: S16
A60: 59 | B60: KYOCERA | C60: KYOCERA ECOSYS PA6000x | D60: 3 | E60: メンテナンス | F60: — | G60: メンテナンスキット MK-3381 | H60: MK-3381 | J60: 500000 | K60: 24300 | L60: メーカー標準価格（税別） | M60: あり（リターン方式） | N60: MK-3381 | O60: =IF($N60="","—",IF(COUNTIF(台帳マスタ!$A:$A,$N60)>0,"登録あり","未登録")) | P60: 約50万ページごと。ドラム・現像を含む | Q60: S16
A61: 60 | B61: Ricoh | C61: Ricoh IMC3500 | D61: 1 | E61: トナー | F61: ブラック | G61: RICOH MP トナー ブラック C3503 | H61: C3503 | I61: 600249 | L61: — | M61: あり | N61: C3503 | O61: =IF($N61="","—",IF(COUNTIF(台帳マスタ!$A:$A,$N61)>0,"登録あり","未登録")) | P61: 品種コードは販売店表記。保守契約の種別で品目が変わる | Q61: S26
A62: 61 | B62: Ricoh | C62: Ricoh IMC3500 | D62: 1 | E62: トナー | F62: イエロー | G62: RICOH MP トナー イエロー C3503 | H62: C3503 | I62: 600250 | L62: — | M62: あり | N62: C3503 | O62: =IF($N62="","—",IF(COUNTIF(台帳マスタ!$A:$A,$N62)>0,"登録あり","未登録")) | P62: 品種コードは販売店表記。保守契約の種別で品目が変わる | Q62: S26
A63: 62 | B63: Ricoh | C63: Ricoh IMC3500 | D63: 1 | E63: トナー | F63: マゼンタ | G63: RICOH MP トナー マゼンタ C3503 | H63: C3503 | I63: 600251 | L63: — | M63: あり | N63: C3503 | O63: =IF($N63="","—",IF(COUNTIF(台帳マスタ!$A:$A,$N63)>0,"登録あり","未登録")) | P63: 品種コードは販売店表記。保守契約の種別で品目が変わる | Q63: S26
A64: 63 | B64: Ricoh | C64: Ricoh IMC3500 | D64: 1 | E64: トナー | F64: シアン | G64: RICOH MP トナー シアン C3503 | H64: C3503 | I64: 600252 | L64: — | M64: あり | N64: C3503 | O64: =IF($N64="","—",IF(COUNTIF(台帳マスタ!$A:$A,$N64)>0,"登録あり","未登録")) | P64: 品種コードは販売店表記。保守契約の種別で品目が変わる | Q64: S26
A65: 64 | B65: Ricoh | C65: Ricoh IMC3500 | D65: 1 | E65: 廃トナー | F65: — | G65: 廃トナーボトル IM C6000（IM C2000〜C6000 共通） | H65: IM C6000 | J65: 40000 | L65: — | M65: あり | N65: IM C6000 | O65: =IF($N65="","—",IF(COUNTIF(台帳マスタ!$A:$A,$N65)>0,"登録あり","未登録")) | P65: 価格は販売担当に確認 | Q65: S09
A66: 65 | B66: Ricoh | C66: Ricoh IPSio SP 4510 | D66: 1 | E66: トナー | F66: ブラック | G66: RICOH SP トナー 4500L | H66: 4500L | I66: 600546 | J66: 3000 | K66: 13300 | L66: メーカー標準価格（税別） | M66: あり | N66: 4500L | O66: =IF($N66="","—",IF(COUNTIF(台帳マスタ!$A:$A,$N66)>0,"登録あり","未登録")) | Q66: S05
A67: 66 | B67: Ricoh | C67: Ricoh IPSio SP 4510 | D67: 1 | E67: トナー | F67: ブラック | G67: RICOH SP トナー 4500 | H67: 4500 | I67: 600545 | J67: 6000 | K67: 21900 | L67: メーカー標準価格（税別） | M67: あり | N67: 4500 | O67: =IF($N67="","—",IF(COUNTIF(台帳マスタ!$A:$A,$N67)>0,"登録あり","未登録")) | Q67: S05
A68: 67 | B68: Ricoh | C68: Ricoh IPSio SP 4510 | D68: 1 | E68: トナー | F68: ブラック | G68: RICOH SP トナー 4500H（大容量） | H68: 4500H | I68: 600544 | J68: 10000 | K68: 34300 | L68: メーカー標準価格（税別） | M68: あり | N68: トナー4500H | O68: =IF($N68="","—",IF(COUNTIF(台帳マスタ!$A:$A,$N68)>0,"登録あり","未登録")) | Q68: S05
A69: 68 | B69: Ricoh | C69: Ricoh IPSio SP 4510 | D69: 1 | E69: ドラム | F69: — | G69: RICOH SP ドラムユニット 4500 | H69: ドラムユニット4500 | I69: 512560 | J69: 20000 | K69: 11100 | L69: メーカー標準価格（税別） | M69: あり | N69: ドラムユニット4500 | O69: =IF($N69="","—",IF(COUNTIF(台帳マスタ!$A:$A,$N69)>0,"登録あり","未登録")) | Q69: S05
A70: 69 | B70: Ricoh | C70: Ricoh SP 4510 | D70: 2 | E70: トナー | F70: ブラック | G70: RICOH SP トナー 4500L | H70: 4500L | I70: 600546 | J70: 3000 | K70: 13300 | L70: メーカー標準価格（税別） | M70: あり | N70: 4500L | O70: =IF($N70="","—",IF(COUNTIF(台帳マスタ!$A:$A,$N70)>0,"登録あり","未登録")) | Q70: S05
A71: 70 | B71: Ricoh | C71: Ricoh SP 4510 | D71: 2 | E71: トナー | F71: ブラック | G71: RICOH SP トナー 4500 | H71: 4500 | I71: 600545 | J71: 6000 | K71: 21900 | L71: メーカー標準価格（税別） | M71: あり | N71: 4500 | O71: =IF($N71="","—",IF(COUNTIF(台帳マスタ!$A:$A,$N71)>0,"登録あり","未登録")) | Q71: S05
A72: 71 | B72: Ricoh | C72: Ricoh SP 4510 | D72: 2 | E72: トナー | F72: ブラック | G72: RICOH SP トナー 4500H（大容量） | H72: 4500H | I72: 600544 | J72: 10000 | K72: 34300 | L72: メーカー標準価格（税別） | M72: あり | N72: トナー4500H | O72: =IF($N72="","—",IF(COUNTIF(台帳マスタ!$A:$A,$N72)>0,"登録あり","未登録")) | Q72: S05
A73: 72 | B73: Ricoh | C73: Ricoh SP 4510 | D73: 2 | E73: ドラム | F73: — | G73: RICOH SP ドラムユニット 4500 | H73: ドラムユニット4500 | I73: 512560 | J73: 20000 | K73: 11100 | L73: メーカー標準価格（税別） | M73: あり | N73: ドラムユニット4500 | O73: =IF($N73="","—",IF(COUNTIF(台帳マスタ!$A:$A,$N73)>0,"登録あり","未登録")) | Q73: S05
A74: 73 | B74: Ricoh | C74: Ricoh P C301SF | D74: 3 | E74: トナー | F74: ブラック | G74: トナーカートリッジ ブラック P C300 | H74: P C300 | I74: 514233 | J74: 2800 | K74: 9400 | L74: メーカー標準価格（税別） | M74: あり | N74: P C300 | O74: =IF($N74="","—",IF(COUNTIF(台帳マスタ!$A:$A,$N74)>0,"登録あり","未登録")) | P74: 標準容量 | Q74: S01
A75: 74 | B75: Ricoh | C75: Ricoh P C301SF | D75: 3 | E75: トナー | F75: シアン | G75: トナーカートリッジ シアン P C300 | H75: P C300 | I75: 514234 | J75: 2800 | K75: 11300 | L75: メーカー標準価格（税別） | M75: あり | N75: P C300 | O75: =IF($N75="","—",IF(COUNTIF(台帳マスタ!$A:$A,$N75)>0,"登録あり","未登録")) | P75: 標準容量 | Q75: S01
A76: 75 | B76: Ricoh | C76: Ricoh P C301SF | D76: 3 | E76: トナー | F76: マゼンタ | G76: トナーカートリッジ マゼンタ P C300 | H76: P C300 | I76: 514235 | J76: 2800 | K76: 11300 | L76: メーカー標準価格（税別） | M76: あり | N76: P C300 | O76: =IF($N76="","—",IF(COUNTIF(台帳マスタ!$A:$A,$N76)>0,"登録あり","未登録")) | P76: 標準容量 | Q76: S01
A77: 76 | B77: Ricoh | C77: Ricoh P C301SF | D77: 3 | E77: トナー | F77: イエロー | G77: トナーカートリッジ イエロー P C300 | H77: P C300 | I77: 514236 | J77: 2800 | K77: 11300 | L77: メーカー標準価格（税別） | M77: あり | N77: P C300 | O77: =IF($N77="","—",IF(COUNTIF(台帳マスタ!$A:$A,$N77)>0,"登録あり","未登録")) | P77: 標準容量 | Q77: S01
A78: 77 | B78: Ricoh | C78: Ricoh P C301SF | D78: 3 | E78: トナー | F78: ブラック | G78: トナーカートリッジ ブラック P C300H | H78: P C300H | I78: 514229 | J78: 6200 | K78: 18100 | L78: メーカー標準価格（税別） | M78: あり | N78: PC300H-BK | O78: =IF($N78="","—",IF(COUNTIF(台帳マスタ!$A:$A,$N78)>0,"登録あり","未登録")) | P78: 大容量 | Q78: S01
A79: 78 | B79: Ricoh | C79: Ricoh P C301SF | D79: 3 | E79: トナー | F79: シアン | G79: トナーカートリッジ シアン P C300H | H79: P C300H | I79: 514230 | J79: 6200 | K79: 18700 | L79: メーカー標準価格（税別） | M79: あり | N79: PC300H-C | O79: =IF($N79="","—",IF(COUNTIF(台帳マスタ!$A:$A,$N79)>0,"登録あり","未登録")) | P79: 大容量 | Q79: S01
A80: 79 | B80: Ricoh | C80: Ricoh P C301SF | D80: 3 | E80: トナー | F80: マゼンタ | G80: トナーカートリッジ マゼンタ P C300H | H80: P C300H | I80: 514231 | J80: 6200 | K80: 18700 | L80: メーカー標準価格（税別） | M80: あり | N80: PC300H-M | O80: =IF($N80="","—",IF(COUNTIF(台帳マスタ!$A:$A,$N80)>0,"登録あり","未登録")) | P80: 大容量 | Q80: S01
A81: 80 | B81: Ricoh | C81: Ricoh P C301SF | D81: 3 | E81: トナー | F81: イエロー | G81: トナーカートリッジ イエロー P C300H | H81: P C300H | I81: 514232 | J81: 6200 | K81: 18700 | L81: メーカー標準価格（税別） | M81: あり | N81: PC300H-Y | O81: =IF($N81="","—",IF(COUNTIF(台帳マスタ!$A:$A,$N81)>0,"登録あり","未登録")) | P81: 大容量 | Q81: S01
A82: 81 | B82: Ricoh | C82: Ricoh P C301SF | D82: 3 | E82: 廃トナー | F82: — | G82: 廃トナーボトル C220 | H82: C220 | I82: 515285 | J82: 25000 | K82: 3400 | L82: メーカー標準価格（税別） | M82: あり | N82: 廃トナーボトルC220 | O82: =IF($N82="","—",IF(COUNTIF(台帳マスタ!$A:$A,$N82)>0,"登録あり","未登録")) | Q82: S01
A83: 82 | B83: Ricoh | C83: Ricoh P501 | D83: 12 | E83: トナー | F83: ブラック | G83: RICOH トナー P 500L | H83: P 500L | I83: 514202 | J83: 3000 | K83: 13600 | L83: メーカー標準価格（税別） | M83: あり | N83: P 500L | O83: =IF($N83="","—",IF(COUNTIF(台帳マスタ!$A:$A,$N83)>0,"登録あり","未登録")) | Q83: S02
A84: 83 | B84: Ricoh | C84: Ricoh P501 | D84: 12 | E84: トナー | F84: ブラック | G84: RICOH トナー P 500 | H84: P 500 | I84: 514203 | J84: 10000 | K84: 37500 | L84: メーカー標準価格（税別） | M84: あり | N84: P 500 | O84: =IF($N84="","—",IF(COUNTIF(台帳マスタ!$A:$A,$N84)>0,"登録あり","未登録")) | Q84: S02
A85: 84 | B85: Ricoh | C85: Ricoh P501 | D85: 12 | E85: トナー | F85: ブラック | G85: RICOH トナー P 500H（大容量） | H85: P 500H | I85: 514204 | J85: 14000 | K85: 49400 | L85: メーカー標準価格（税別） | M85: あり | N85: P500H | O85: =IF($N85="","—",IF(COUNTIF(台帳マスタ!$A:$A,$N85)>0,"登録あり","未登録")) | Q85: S02
A86: 85 | B86: Ricoh | C86: Ricoh P501 | D86: 12 | E86: ドラム | F86: — | G86: RICOH ドラムユニット P 500 | H86: ドラムユニット P 500 | I86: 514205 | J86: 40000 | K86: 17700 | L86: メーカー標準価格（税別） | M86: あり | N86: ドラムユニットP500 | O86: =IF($N86="","—",IF(COUNTIF(台帳マスタ!$A:$A,$N86)>0,"登録あり","未登録")) | P86: 約4万ページで交換 | Q86: S02
A87: 86 | B87: Ricoh | C87: Ricoh SP 3610 | D87: 1 | E87: トナー | F87: ブラック | G87: RICOH SP トナー 4500L | H87: 4500L | I87: 600546 | J87: 3000 | K87: 13300 | L87: メーカー標準価格（税別） | M87: あり | N87: 4500L | O87: =IF($N87="","—",IF(COUNTIF(台帳マスタ!$A:$A,$N87)>0,"登録あり","未登録")) | Q87: S03
A88: 87 | B88: Ricoh | C88: Ricoh SP 3610 | D88: 1 | E88: トナー | F88: ブラック | G88: RICOH SP トナー 4500 | H88: 4500 | I88: 600545 | J88: 6000 | K88: 21900 | L88: メーカー標準価格（税別） | M88: あり | N88: 4500 | O88: =IF($N88="","—",IF(COUNTIF(台帳マスタ!$A:$A,$N88)>0,"登録あり","未登録")) | Q88: S03
A89: 88 | B89: Ricoh | C89: Ricoh SP 3610 | D89: 1 | E89: トナー | F89: ブラック | G89: RICOH SP トナー 4500H（大容量） | H89: 4500H | I89: 600544 | J89: 10000 | K89: 34300 | L89: メーカー標準価格（税別） | M89: あり | N89: トナー4500H | O89: =IF($N89="","—",IF(COUNTIF(台帳マスタ!$A:$A,$N89)>0,"登録あり","未登録")) | P89: SP 3610 の公式消耗品ページには記載なし（SP 4510/4500 用）。要確認 | Q89: S05
A90: 89 | B90: Ricoh | C90: Ricoh SP 3610 | D90: 1 | E90: ドラム | F90: — | G90: RICOH SP ドラムユニット 4500 | H90: ドラムユニット4500 | I90: 512560 | J90: 20000 | K90: 11100 | L90: メーカー標準価格（税別） | M90: あり | N90: ドラムユニット4500 | O90: =IF($N90="","—",IF(COUNTIF(台帳マスタ!$A:$A,$N90)>0,"登録あり","未登録")) | Q90: S03
A91: 90 | B91: Ricoh | C91: Ricoh SP 4310 | D91: 2 | E91: トナー | F91: ブラック | G91: IPSiO SP トナーカートリッジ 4200 | H91: 4200 | I91: 308534 | J91: 6000 | K91: 33100 | L91: メーカー標準価格（税別） | M91: あり | N91: トナー4200 | O91: =IF($N91="","—",IF(COUNTIF(台帳マスタ!$A:$A,$N91)>0,"登録あり","未登録")) | Q91: S04
A92: 91 | B92: Ricoh | C92: Ricoh SP 4310 | D92: 2 | E92: トナー | F92: ブラック | G92: IPSiO SP トナーカートリッジ 4200H（大容量） | H92: 4200H | I92: 308535 | J92: 12000 | K92: 53000 | L92: メーカー標準価格（税別） | M92: あり | N92: 4200H | O92: =IF($N92="","—",IF(COUNTIF(台帳マスタ!$A:$A,$N92)>0,"登録あり","未登録")) | Q92: S04
A93: 92 | B93: Ricoh | C93: Ricoh SP 4310 | D93: 2 | E93: トナー | F93: ブラック | G93: IPSiO SPEC トナーカートリッジ 4200 | H93: 4200 SPEC | I93: 308636 | J93: 6000 | K93: 29900 | L93: メーカー標準価格（税別） | M93: あり | N93: 4200 SPEC | O93: =IF($N93="","—",IF(COUNTIF(台帳マスタ!$A:$A,$N93)>0,"登録あり","未登録")) | P93: 使用後にリコーへ返却する前提の廉価品 | Q93: S04
A94: 93 | B94: Ricoh | C94: Ricoh SP 4310 | D94: 2 | E94: トナー | F94: ブラック | G94: IPSiO SPEC トナーカートリッジ 4200H | H94: 4200H SPEC | I94: 308637 | J94: 12000 | K94: 47700 | L94: メーカー標準価格（税別） | M94: あり | N94: 4200H SPEC | O94: =IF($N94="","—",IF(COUNTIF(台帳マスタ!$A:$A,$N94)>0,"登録あり","未登録")) | P94: 使用後にリコーへ返却する前提の廉価品 | Q94: S04
A95: 94 | B95: Ricoh | C95: Ricoh SP 4310 | D95: 2 | E95: ドラム | F95: — | G95: （公式消耗品ページに感光体の記載なし） | H95: — | L95: — | M95: あり | O95: =IF($N95="","—",IF(COUNTIF(台帳マスタ!$A:$A,$N95)>0,"登録あり","未登録")) | P95: サービス部品扱いとみられる | Q95: S04
A96: 95 | B96: Ricoh | C96: Ricoh SP C320 | D96: 1 | E96: トナー | F96: ブラック | G96: IPSiO SP トナー ブラック C310 | H96: C310 | I96: 308504 | J96: 2200 | K96: 8300 | L96: メーカー標準価格（税別） | M96: あり | N96: C310 | O96: =IF($N96="","—",IF(COUNTIF(台帳マスタ!$A:$A,$N96)>0,"登録あり","未登録")) | P96: 標準容量 | Q96: S06
A97: 96 | B97: Ricoh | C97: Ricoh SP C320 | D97: 1 | E97: トナー | F97: シアン | G97: IPSiO SP トナー シアン C310 | H97: C310 | I97: 308505 | J97: 2200 | K97: 10000 | L97: メーカー標準価格（税別） | M97: あり | N97: C310 | O97: =IF($N97="","—",IF(COUNTIF(台帳マスタ!$A:$A,$N97)>0,"登録あり","未登録")) | P97: 標準容量 | Q97: S06
A98: 97 | B98: Ricoh | C98: Ricoh SP C320 | D98: 1 | E98: トナー | F98: マゼンタ | G98: IPSiO SP トナー マゼンタ C310 | H98: C310 | I98: 308506 | J98: 2200 | K98: 10000 | L98: メーカー標準価格（税別） | M98: あり | N98: C310 | O98: =IF($N98="","—",IF(COUNTIF(台帳マスタ!$A:$A,$N98)>0,"登録あり","未登録")) | P98: 標準容量 | Q98: S06
A99: 98 | B99: Ricoh | C99: Ricoh SP C320 | D99: 1 | E99: トナー | F99: イエロー | G99: IPSiO SP トナー イエロー C310 | H99: C310 | I99: 308507 | J99: 2200 | K99: 10000 | L99: メーカー標準価格（税別） | M99: あり | N99: C310 | O99: =IF($N99="","—",IF(COUNTIF(台帳マスタ!$A:$A,$N99)>0,"登録あり","未登録")) | P99: 標準容量 | Q99: S06
A100: 99 | B100: Ricoh | C100: Ricoh SP C320 | D100: 1 | E100: トナー | F100: ブラック | G100: IPSiO SP トナー ブラック C310H | H100: C310H | I100: 308500 | J100: 5000 | K100: 16100 | L100: メーカー標準価格（税別） | M100: あり | N100: C310H-BK | O100: =IF($N100="","—",IF(COUNTIF(台帳マスタ!$A:$A,$N100)>0,"登録あり","未登録")) | P100: 大容量 | Q100: S06
...

Sheet 機種サマリー
A1: 機種別サマリー（台帳 62 台 / 22 機種）
A2: 調査日 2026-08-21。台数は端末台帳の登録数。「点数」は本表の消耗品一覧を数えたもの。
A4: メーカー | B4: 機種（台帳の型番） | C4: 台数 | D4: 消耗品点数 | E4: うちトナー/インク | F4: うちドラム | G4: うち廃トナー・回収 | H4: うちメンテ・ベルト | I4: 台帳マスタ未登録 | J4: リサイクル/互換 | K4: リサイクルの状況 | L4: 注意点 | M4: 出典
A5: Brother | B5: Brother HL-L3230CDW | C5: 1 | D5: =COUNTIF(消耗品一覧!$C:$C,$B5) | E5: =COUNTIFS(消耗品一覧!$C:$C,$B5,消耗品一覧!$E:$E,"トナー")+COUNTIFS(消耗品一覧!$C:$C,$B5,消耗品一覧!$E:$E,"インク") | F5: =COUNTIFS(消耗品一覧!$C:$C,$B5,消耗品一覧!$E:$E,"ドラム") | G5: =COUNTIFS(消耗品一覧!$C:$C,$B5,消耗品一覧!$E:$E,"廃トナー") | H5: =COUNTIFS(消耗品一覧!$C:$C,$B5,消耗品一覧!$E:$E,"メンテナンス")+COUNTIFS(消耗品一覧!$C:$C,$B5,消耗品一覧!$E:$E,"ベルト") | I5: =COUNTIFS(消耗品一覧!$C:$C,$B5,消耗品一覧!$O:$O,"未登録") | J5: あり | K5: TN-293/TN-297 の各色に互換・リサイクル品が流通。ドラム DR-293CL も再生品あり | L5: 黒の大容量（TN-297BK）は無く、黒は TN-293BK のみ。ベルトユニット BU-223CL と廃トナーボックス WT-223CL も定期交換部品。 | M5: S34
A6: Canon | B6: Canon LBP-6710 | C6: 1 | D6: =COUNTIF(消耗品一覧!$C:$C,$B6) | E6: =COUNTIFS(消耗品一覧!$C:$C,$B6,消耗品一覧!$E:$E,"トナー")+COUNTIFS(消耗品一覧!$C:$C,$B6,消耗品一覧!$E:$E,"インク") | F6: =COUNTIFS(消耗品一覧!$C:$C,$B6,消耗品一覧!$E:$E,"ドラム") | G6: =COUNTIFS(消耗品一覧!$C:$C,$B6,消耗品一覧!$E:$E,"廃トナー") | H6: =COUNTIFS(消耗品一覧!$C:$C,$B6,消耗品一覧!$E:$E,"メンテナンス")+COUNTIFS(消耗品一覧!$C:$C,$B6,消耗品一覧!$E:$E,"ベルト") | I6: =COUNTIFS(消耗品一覧!$C:$C,$B6,消耗品一覧!$O:$O,"未登録") | J6: あり | K6: トナーカートリッジ524/524II のリサイクル品が流通 | L6: 台帳表記は LBP-6710。実機は Satera LBP6710i。カートリッジはドラム一体型で、感光体の別売なし。 | M6: S32
A7: Canon | B7: Canon iR-ADV C3520F | C7: 10 | D7: =COUNTIF(消耗品一覧!$C:$C,$B7) | E7: =COUNTIFS(消耗品一覧!$C:$C,$B7,消耗品一覧!$E:$E,"トナー")+COUNTIFS(消耗品一覧!$C:$C,$B7,消耗品一覧!$E:$E,"インク") | F7: =COUNTIFS(消耗品一覧!$C:$C,$B7,消耗品一覧!$E:$E,"ドラム") | G7: =COUNTIFS(消耗品一覧!$C:$C,$B7,消耗品一覧!$E:$E,"廃トナー") | H7: =COUNTIFS(消耗品一覧!$C:$C,$B7,消耗品一覧!$E:$E,"メンテナンス")+COUNTIFS(消耗品一覧!$C:$C,$B7,消耗品一覧!$E:$E,"ベルト") | I7: =COUNTIFS(消耗品一覧!$C:$C,$B7,消耗品一覧!$O:$O,"未登録") | J7: あり | K7: NPG-67 のリサイクルトナーが各社にあり（4色）。WT-202 は純正のみが基本 | L7: 複合機。国内では感光体・定着などは保守契約でサービス交換が基本。一般に買えるのはトナー NPG-67 と回収トナー容器 WT-202。 | M7: S22
A8: Canon | B8: Canon iR-ADV C3530F | C8: 4 | D8: =COUNTIF(消耗品一覧!$C:$C,$B8) | E8: =COUNTIFS(消耗品一覧!$C:$C,$B8,消耗品一覧!$E:$E,"トナー")+COUNTIFS(消耗品一覧!$C:$C,$B8,消耗品一覧!$E:$E,"インク") | F8: =COUNTIFS(消耗品一覧!$C:$C,$B8,消耗品一覧!$E:$E,"ドラム") | G8: =COUNTIFS(消耗品一覧!$C:$C,$B8,消耗品一覧!$E:$E,"廃トナー") | H8: =COUNTIFS(消耗品一覧!$C:$C,$B8,消耗品一覧!$E:$E,"メンテナンス")+COUNTIFS(消耗品一覧!$C:$C,$B8,消耗品一覧!$E:$E,"ベルト") | I8: =COUNTIFS(消耗品一覧!$C:$C,$B8,消耗品一覧!$O:$O,"未登録") | J8: あり | K8: NPG-67 のリサイクルトナー（C3520F と共通） | L8: 消耗品は C3520F と共通（NPG-67 / WT-202）。 | M8: S22
A9: EPSON | B9: EPSON PX-M791FT | C9: 3 | D9: =COUNTIF(消耗品一覧!$C:$C,$B9) | E9: =COUNTIFS(消耗品一覧!$C:$C,$B9,消耗品一覧!$E:$E,"トナー")+COUNTIFS(消耗品一覧!$C:$C,$B9,消耗品一覧!$E:$E,"インク") | F9: =COUNTIFS(消耗品一覧!$C:$C,$B9,消耗品一覧!$E:$E,"ドラム") | G9: =COUNTIFS(消耗品一覧!$C:$C,$B9,消耗品一覧!$E:$E,"廃トナー") | H9: =COUNTIFS(消耗品一覧!$C:$C,$B9,消耗品一覧!$E:$E,"メンテナンス")+COUNTIFS(消耗品一覧!$C:$C,$B9,消耗品一覧!$E:$E,"ベルト") | I9: =COUNTIFS(消耗品一覧!$C:$C,$B9,消耗品一覧!$O:$O,"未登録") | J9: あり（互換） | K9: IT08 系の互換インクボトル、PXMB9 の互換メンテナンスボックスあり | L9: エコタンク（インクボトル）。純正はオープン価格で、価格は販売店見積り。 | M9: S28
A10: EPSON | B10: EPSON PX-S381 | C10: 1 | D10: =COUNTIF(消耗品一覧!$C:$C,$B10) | E10: =COUNTIFS(消耗品一覧!$C:$C,$B10,消耗品一覧!$E:$E,"トナー")+COUNTIFS(消耗品一覧!$C:$C,$B10,消耗品一覧!$E:$E,"インク") | F10: =COUNTIFS(消耗品一覧!$C:$C,$B10,消耗品一覧!$E:$E,"ドラム") | G10: =COUNTIFS(消耗品一覧!$C:$C,$B10,消耗品一覧!$E:$E,"廃トナー") | H10: =COUNTIFS(消耗品一覧!$C:$C,$B10,消耗品一覧!$E:$E,"メンテナンス")+COUNTIFS(消耗品一覧!$C:$C,$B10,消耗品一覧!$E:$E,"ベルト") | I10: =COUNTIFS(消耗品一覧!$C:$C,$B10,消耗品一覧!$O:$O,"未登録") | J10: あり（互換） | K10: IP04KA 互換インクパック、PXMB8 互換メンテナンスボックスあり | L10: 台帳の型番は PX-S381L の表記違いと思われる（同一の IP04KA / PXMB8）。台帳を直すか確認したい。 | M10: S30
A11: EPSON | B11: EPSON PX-S381L | C11: 4 | D11: =COUNTIF(消耗品一覧!$C:$C,$B11) | E11: =COUNTIFS(消耗品一覧!$C:$C,$B11,消耗品一覧!$E:$E,"トナー")+COUNTIFS(消耗品一覧!$C:$C,$B11,消耗品一覧!$E:$E,"インク") | F11: =COUNTIFS(消耗品一覧!$C:$C,$B11,消耗品一覧!$E:$E,"ドラム") | G11: =COUNTIFS(消耗品一覧!$C:$C,$B11,消耗品一覧!$E:$E,"廃トナー") | H11: =COUNTIFS(消耗品一覧!$C:$C,$B11,消耗品一覧!$E:$E,"メンテナンス")+COUNTIFS(消耗品一覧!$C:$C,$B11,消耗品一覧!$E:$E,"ベルト") | I11: =COUNTIFS(消耗品一覧!$C:$C,$B11,消耗品一覧!$O:$O,"未登録") | J11: あり（互換） | K11: IP04KA 互換インクパック、PXMB8 互換メンテナンスボックスあり | L11: インクパックは IP04KA。旧 IP03KB も使用可。 | M11: S30
A12: FUJITSU | B12: FUJITSU XL-9322 | C12: 1 | D12: =COUNTIF(消耗品一覧!$C:$C,$B12) | E12: =COUNTIFS(消耗品一覧!$C:$C,$B12,消耗品一覧!$E:$E,"トナー")+COUNTIFS(消耗品一覧!$C:$C,$B12,消耗品一覧!$E:$E,"インク") | F12: =COUNTIFS(消耗品一覧!$C:$C,$B12,消耗品一覧!$E:$E,"ドラム") | G12: =COUNTIFS(消耗品一覧!$C:$C,$B12,消耗品一覧!$E:$E,"廃トナー") | H12: =COUNTIFS(消耗品一覧!$C:$C,$B12,消耗品一覧!$E:$E,"メンテナンス")+COUNTIFS(消耗品一覧!$C:$C,$B12,消耗品一覧!$E:$E,"ベルト") | I12: =COUNTIFS(消耗品一覧!$C:$C,$B12,消耗品一覧!$O:$O,"未登録") | J12: あり | K12: LB321A/LB321M とドラム LB321 のリサイクル品あり（純正の 1/6 程度の例） | L12: 大容量トナーの型番が資料により LB321M / LB321B と分かれる。発注前に実機のラベルで要確認。 | M12: S24
A13: FujiXerox | B13: FujiXerox DocuPrint CP500 d | C13: 1 | D13: =COUNTIF(消耗品一覧!$C:$C,$B13) | E13: =COUNTIFS(消耗品一覧!$C:$C,$B13,消耗品一覧!$E:$E,"トナー")+COUNTIFS(消耗品一覧!$C:$C,$B13,消耗品一覧!$E:$E,"インク") | F13: =COUNTIFS(消耗品一覧!$C:$C,$B13,消耗品一覧!$E:$E,"ドラム") | G13: =COUNTIFS(消耗品一覧!$C:$C,$B13,消耗品一覧!$E:$E,"廃トナー") | H13: =COUNTIFS(消耗品一覧!$C:$C,$B13,消耗品一覧!$E:$E,"メンテナンス")+COUNTIFS(消耗品一覧!$C:$C,$B13,消耗品一覧!$E:$E,"ベルト") | I13: =COUNTIFS(消耗品一覧!$C:$C,$B13,消耗品一覧!$O:$O,"未登録") | J13: あり | K13: CT203057〜60 のリサイクルトナー、CT351149〜52 の再生ドラムが流通 | L13: 現・富士フイルムビジネスイノベーション。標準容量と大容量の 2 系統。ドラムは色ごとに別売。 | M13: S33
A14: HP | B14: HP LaserJet M601 | C14: 1 | D14: =COUNTIF(消耗品一覧!$C:$C,$B14) | E14: =COUNTIFS(消耗品一覧!$C:$C,$B14,消耗品一覧!$E:$E,"トナー")+COUNTIFS(消耗品一覧!$C:$C,$B14,消耗品一覧!$E:$E,"インク") | F14: =COUNTIFS(消耗品一覧!$C:$C,$B14,消耗品一覧!$E:$E,"ドラム") | G14: =COUNTIFS(消耗品一覧!$C:$C,$B14,消耗品一覧!$E:$E,"廃トナー") | H14: =COUNTIFS(消耗品一覧!$C:$C,$B14,消耗品一覧!$E:$E,"メンテナンス")+COUNTIFS(消耗品一覧!$C:$C,$B14,消耗品一覧!$E:$E,"ベルト") | I14: =COUNTIFS(消耗品一覧!$C:$C,$B14,消耗品一覧!$O:$O,"未登録") | J14: あり | K14: CE390A/CE390X は互換・リサイクル品が非常に多い | L14: CE390A（90A）と大容量 CE390X（90X）。定着を含むメンテナンスキット CF064A あり。 | M14: S28
A15: KYOCERA | B15: KYOCERA ECOSYS PA6000x | C15: 3 | D15: =COUNTIF(消耗品一覧!$C:$C,$B15) | E15: =COUNTIFS(消耗品一覧!$C:$C,$B15,消耗品一覧!$E:$E,"トナー")+COUNTIFS(消耗品一覧!$C:$C,$B15,消耗品一覧!$E:$E,"インク") | F15: =COUNTIFS(消耗品一覧!$C:$C,$B15,消耗品一覧!$E:$E,"ドラム") | G15: =COUNTIFS(消耗品一覧!$C:$C,$B15,消耗品一覧!$E:$E,"廃トナー") | H15: =COUNTIFS(消耗品一覧!$C:$C,$B15,消耗品一覧!$E:$E,"メンテナンス")+COUNTIFS(消耗品一覧!$C:$C,$B15,消耗品一覧!$E:$E,"ベルト") | I15: =COUNTIFS(消耗品一覧!$C:$C,$B15,消耗品一覧!$O:$O,"未登録") | J15: あり（リターン方式） | K15: TK-3431 リサイクルは使用済みを返却する方式が主。廃トナーBOX 同梱の商品あり | L15: トナー TK-3431 は 2 本単位の販売。ドラム・廃トナーボックス単体の公式掲載はなく、MK-3381 メンテナンスキットで対応。 | M15: S31
A16: Ricoh | B16: Ricoh IMC3500 | C16: 1 | D16: =COUNTIF(消耗品一覧!$C:$C,$B16) | E16: =COUNTIFS(消耗品一覧!$C:$C,$B16,消耗品一覧!$E:$E,"トナー")+COUNTIFS(消耗品一覧!$C:$C,$B16,消耗品一覧!$E:$E,"インク") | F16: =COUNTIFS(消耗品一覧!$C:$C,$B16,消耗品一覧!$E:$E,"ドラム") | G16: =COUNTIFS(消耗品一覧!$C:$C,$B16,消耗品一覧!$E:$E,"廃トナー") | H16: =COUNTIFS(消耗品一覧!$C:$C,$B16,消耗品一覧!$E:$E,"メンテナンス")+COUNTIFS(消耗品一覧!$C:$C,$B16,消耗品一覧!$E:$E,"ベルト") | I16: =COUNTIFS(消耗品一覧!$C:$C,$B16,消耗品一覧!$O:$O,"未登録") | J16: あり | K16: C3503 各色のリサイクルトナーが流通 | L16: 複合機。保守契約の種別でトナーの品目が変わる（パフォーマンス契約用＝MP P トナー、スポット保守契約用＝MP トナー）。価格は販売担当に確認。 | M16: S27
... A26: Ricoh | B26: Ricoh SP C750 | C26: 1 | D26: =COUNTIF(消耗品一覧!$C:$C,$B26) | E26: =COUNTIFS(消耗品一覧!$C:$C,$B26,消耗品一覧!$E:$E,"トナー")+COUNTIFS(消耗品一覧!$C:$C,$B26,消耗品一覧!$E:$E,"インク") | F26: =COUNTIFS(消耗品一覧!$C:$C,$B26,消耗品一覧!$E:$E,"ドラム") | G26: =COUNTIFS(消耗品一覧!$C:$C,$B26,消耗品一覧!$E:$E,"廃トナー") | H26: =COUNTIFS(消耗品一覧!$C:$C,$B26,消耗品一覧!$E:$E,"メンテナンス")+COUNTIFS(消耗品一覧!$C:$C,$B26,消耗品一覧!$E:$E,"ベルト") | I26: =COUNTIFS(消耗品一覧!$C:$C,$B26,消耗品一覧!$O:$O,"未登録") | J26: あり | K26: C740H 各色のリサイクルトナーあり | L26: SP C751/C750 系。ドラムはカラー用とブラック用で別。 | M26: S28
B27: 合計 | C27: =SUM(C5:C26) | D27: =SUM(D5:D26) | E27: =SUM(E5:E26) | F27: =SUM(F5:F26) | G27: =SUM(G5:G26) | H27: =SUM(H5:H26) | I27: =SUM(I5:I26)

Sheet 台帳マスタ
A1: トナーマスタ（システムに登録済みの品番）
A2: 2026-08-21 時点の GET /api/toners。消耗品一覧の「台帳マスタ」列はこの A 列を COUNTIF で引いている。
A4: トナーID | B4: トナー名 | C4: 色 | D4: 区分 | E4: 登録価格（税別）
A5: KX-FAN190W | B5: KX-FAN190W（KX-FAN190W） | D5: 純正 | E5: 1130
A6: HP728BBK | B6: インクカートリッジ HP728BBK（300ml）（HP 728（総務：ポスター用）） | C6: ブラック | D6: 純正 | E6: 17000
A7: HP728C | B7: インクカートリッジ HP728C（130ml）（HP 728（総務：ポスター用）） | C7: シアン | D7: 純正 | E7: 9100
A8: HP728M | B8: インクカートリッジ HP728M（130ml）（HP 728（総務：ポスター用）） | C8: マゼンタ | D8: 純正 | E8: 9100
A9: HP728Y | B9: インクカートリッジ HP728Y（130ml）（HP 728（総務：ポスター用）） | C9: イエロー | D9: 純正 | E9: 9100
A10: IB09CB | B10: インクカートリッジ IB09CB（PX-S730） | C10: シアン | D10: 純正 | E10: 1100
A11: IB09CL4B | B11: インクカートリッジ IB09CL4B（PX-S730） | C11: 4色パック | D11: 純正 | E11: 7200
A12: IB09KB | B12: インクカートリッジ IB09KB（PX-S730） | C12: ブラック | D12: 純正 | E12: 2400
A13: IB09MB | B13: インクカートリッジ IB09MB（PX-S730） | C13: マゼンタ | D13: 純正 | E13: 1100
A14: IB09YB | B14: インクカートリッジ IB09YB（PX-S730） | C14: イエロー | D14: 純正 | E14: 1100
A15: IB10CA | B15: インクカートリッジ IB10CA（EW-M530F） | C15: シアン | D15: 再生 | E15: 900
A16: IB10CL4A | B16: インクカートリッジ IB10CL4A（EW-M530F） | C16: 4色パック | D16: 再生 | E16: 4900
A17: IB10KA | B17: インクカートリッジ IB10KA（EW-M530F） | C17: ブラック | D17: 再生 | E17: 2500
... A20: IC4CL69 | B20: インクカートリッジ IC4CL69（糖内科（リブレ用）） | C20: 4色パック | D20: 純正 | E20: 2150
A21: ICBK50 | B21: インクカートリッジ ICBK50（リハビリ：コピー用） | C21: ブラック | D21: 純正
A22: ICBK61 | B22: インクカートリッジ ICBK61（PX205） | C22: ブラック | D22: 再生 | E22: 1000
A23: ICBK62 | B23: インクカートリッジ ICBK62（PX205） | C23: ブラック | D23: 再生 | E23: 640
A24: ICBK69L | B24: インクカートリッジ ICBK69L（糖内科（リブレ用）） | C24: ブラック | D24: 純正 | E24: 930
A25: ICBK75 | B25: インクカートリッジ ICBK75（PX-S740） | C25: ブラック | D25: 再生 | E25: 2000
A26: ICBK84 | B26: インクカートリッジ ICBK84（PX-M780F） | C26: ブラック | D26: 再生 | E26: 1880
A27: ICC50 | B27: インクカートリッジ ICC50（リハビリ：コピー用） | C27: シアン | D27: 純正
A28: ICC62 | B28: インクカートリッジ ICC62（PX205） | C28: シアン | D28: 再生 | E28: 550
A29: ICC69 | B29: インクカートリッジ ICC69（糖内科（リブレ用）） | C29: シアン | D29: 純正 | E29: 580
A30: ICC74 | B30: インクカートリッジ ICC74（PX-S740） | C30: シアン | D30: 再生 | E30: 580
A31: ICC84 | B31: インクカートリッジ ICC84（PX-M780F） | C31: シアン | D31: 再生 | E31: 1280
A32: ICLC50 | B32: インクカートリッジ ICLC50（リハビリ：コピー用） | C32: ライトシアン | D32: 純正
A33: ICLM50 | B33: インクカートリッジ ICLM50（リハビリ：コピー用） | C33: ライトマゼンタ | D33: 純正
A34: ICM50 | B34: インクカートリッジ ICM50（リハビリ：コピー用） | C34: マゼンタ | D34: 純正
A35: ICM62 | B35: インクカートリッジ ICM62（PX205） | C35: マゼンタ | D35: 再生 | E35: 550
A36: ICM69 | B36: インクカートリッジ ICM69（糖内科（リブレ用）） | C36: マゼンタ | D36: 純正 | E36: 580
A37: ICM74 | B37: インクカートリッジ ICM74（PX-S740） | C37: マゼンタ | D37: 再生 | E37: 580
A38: ICM84 | B38: インクカートリッジ ICM84（PX-M780F） | C38: マゼンタ | D38: 再生 | E38: 1280
A39: ICY50 | B39: インクカートリッジ ICY50（リハビリ：コピー用） | C39: イエロー | D39: 純正
A40: ICY62 | B40: インクカートリッジ ICY62（PX205） | C40: イエロー | D40: 再生 | E40: 550
A41: ICY69 | B41: インクカートリッジ ICY69（糖内科（リブレ用）） | C41: イエロー | D41: 純正 | E41: 580
A42: ICY74 | B42: インクカートリッジ ICY74（PX-S740） | C42: イエロー | D42: 再生 | E42: 580
A43: ICY84 | B43: インクカートリッジ ICY84（PX-M780F） | C43: イエロー | D43: 再生 | E43: 1280
A44: IP04KA | B44: インクカートリッジ IP04KA（PX-S381） | C44: ブラック | D44: 純正 | E44: 20000
A45: IT08CA | B45: インクカートリッジ IT08CA（PX-M791FT） | C45: シアン | D45: 再生 | E45: 2200
A46: IT08KA | B46: インクカートリッジ IT08KA（PX-M791FT） | C46: ブラック | D46: 再生 | E46: 4300
A47: IT08MA | B47: インクカートリッジ IT08MA（PX-M791FT） | C47: マゼンタ | D47: 再生 | E47: 2200
A48: IT08YA | B48: インクカートリッジ IT08YA（PX-M791FT） | C48: イエロー | D48: 再生 | E48: 2200
A49: ITH-6CL | B49: インクカートリッジ ITH-6CL（手術室：滅菌機メンテナンス用） | C49: 6色パック | D49: 再生 | E49: 2900
A50: ITH-BK | B50: インクカートリッジ ITH-BK（手術室：滅菌機メンテナンス用） | C50: ブラック | D50: 再生 | E50: 500
A51: ITH-C | B51: インクカートリッジ ITH-C（手術室：滅菌機メンテナンス用） | C51: シアン | D51: 再生 | E51: 500
... A78: C740H-Y | B78: トナーカートリッジ C740H（C750） | C78: イエロー | D78: 再生 | E78: 4800
A79: CE390A | B79: トナーカートリッジ HP 90A（CE390A）（LaserJet M601） | C79: ブラック | D79: 再生
A80: LB321B | B80: トナーカートリッジ LB321B（XL9321） | C80: ブラック | D80: 再生 | E80: 6000
A81: PC300H-BK | B81: トナーカートリッジ P C300H（C301SF） | C81: ブラック | D81: 再生 | E81: 5200
A82: PC300H-C | B82: トナーカートリッジ P C300H（C301SF） | C82: シアン | D82: 再生 | E82: 5200
A83: PC300H-M | B83: トナーカートリッジ P C300H（C301SF） | C83: マゼンタ | D83: 再生 | E83: 5200
A84: PC300H-Y | B84: トナーカートリッジ P C300H（C301SF） | C84: イエロー | D84: 再生 | E84: 5200
A85: P500H | B85: トナーカートリッジ P500H（P501） | C85: ブラック | D85: 再生 | E85: 7200
A86: TK-3191 | B86: トナーカートリッジ TK-3191（ECOSYS P3060dn） | C86: ブラック | D86: 純正 | E86: 19000
A87: TK-3431 | B87: トナーカートリッジ TK-3431（ECOSYS PA6000x） | C87: ブラック | D87: 純正 | E87: 19000
A88: TN-27J | B88: トナーカートリッジ TN-27J（FAX-2840） | D88: 再生 | E88: 2500
A89: TN-293BK | B89: トナーカートリッジ TN-293BK（HL-L3230CDW） | C89: ブラック | D89: 再生 | E89: 3900
A90: TN-297C | B90: トナーカートリッジ TN-297C（HL-L3230CDW） | C90: シアン | D90: 再生 | E90: 4100
A91: TN-297M | B91: トナーカートリッジ TN-297M（HL-L3230CDW） | C91: マゼンタ | D91: 再生 | E91: 4100
A92: TN-297Y | B92: トナーカートリッジ TN-297Y（HL-L3230CDW） | C92: イエロー | D92: 再生 | E92: 4100
A93: TNR-M4G2 | B93: トナーカートリッジ TNR-M4G2（OKI B432） | C93: ブラック | D93: 再生 | E93: 9800
A94: カートリッジ304 | B94: トナーカートリッジ カートリッジ304（Satera D450） | D94: 再生 | E94: 3600
A95: カートリッジ524 | B95: トナーカートリッジ カートリッジ524（生体情報管理モニター） | D95: 再生 | E95: 6000
A96: トナー4200 | B96: トナーカートリッジ トナー4200（SP4310） | C96: ブラック | D96: 再生 | E96: 5400
A97: トナー4500H | B97: トナーカートリッジ トナー4500H（SP4510・SP3610） | C97: ブラック | D97: 再生 | E97: 4600
A98: CT203057 | B98: トナーカートリッジ（大容量） CT203057（DocuPrint CP500d） | C98: ブラック | D98: 再生 | E98: 12300
A99: CT203058 | B99: トナーカートリッジ（大容量） CT203058（DocuPrint CP500d） | C99: シアン | D99: 再生 | E99: 11000
A100: CT203059 | B100: トナーカートリッジ（大容量） CT203059（DocuPrint CP500d） | C100: マゼンタ | D100: 再生 | E100: 11000
A101: CT203060 | B101: トナーカートリッジ（大容量） CT203060（DocuPrint CP500d） | C101: イエロー | D101: 再生 | E101: 11000
A102: CWAA0915 | B102: トナー回収ボトル CWAA0915（DocuPrint CP500d） | D102: 純正 | E102: 2190
A103: CT351149 | B103: ドラムカートリッジ CT351149（DocuPrint CP500d） | C103: ブラック | D103: 純正 | E103: 8500
A104: CT351150 | B104: ドラムカートリッジ CT351150（DocuPrint CP500d） | C104: シアン | D104: 純正 | E104: 8500
A105: CT351151 | B105: ドラムカートリッジ CT351151（DocuPrint CP500d） | C105: マゼンタ | D105: 純正 | E105: 8500
A106: CT351152 | B106: ドラムカートリッジ CT351152（DocuPrint CP500d） | C106: イエロー | D106: 純正 | E106: 8500
A107: LB321 | B107: ドラムカートリッジ LB321（XL9321） | D107: 純正 | E107: 10700
A108: ドラムユニットC740-COLOR | B108: ドラムユニット C740（カラー）（C750） | C108: カラー | D108: 純正 | E108: 37800
A109: ドラムユニットC740-BK | B109: ドラムユニット C740（ブラック）（C750） | C109: ブラック | D109: 純正 | E109: 13000
A110: DR-293CL-BK | B110: ドラムユニット DR-293CL-BK（HL-L3230CDW） | C110: ブラック | D110: 純正 | E110: 5700
A111: DR-293CL-C | B111: ドラムユニット DR-293CL-C（HL-L3230CDW） | C111: シアン | D111: 純正 | E111: 5700
A112: DR-293CL-M | B112: ドラムユニット DR-293CL-M（HL-L3230CDW） | C112: マゼンタ | D112: 純正 | E112: 5700
A113: DR-293CL-Y | B113: ドラムユニット DR-293CL-Y（HL-L3230CDW） | C113: イエロー | D113: 純正 | E113: 5700
A114: DR-293CL | B114: ドラムユニット DR-293CL 4本入り（HL-L3230CDW） | C114: BK,C,M,Y | D114: 純正 | E114: 18000
A115: ドラムユニットP500 | B115: ドラムユニット ドラムユニット P500（P501） | C115: ブラック | D115: 純正 | E115: 12000
A116: ドラムユニット4500 | B116: ドラムユニット ドラムユニット4500（SP4510・SP3610） | D116: 純正 | E116: 8150
A117: DR-22J | B117: ベルトユニット DR-22J（FAX-2840） | D117: 再生 | E117: 4800
A118: MK-3381 | B118: メンテナンスキット MK-3381（ECOSYS PA6000x） | D118: 純正 | E118: 24000
A119: EWMB2 | B119: メンテナンスボックス EWMB2（EW-M530F） | D119: 再生 | E119: 1600
A120: PJMB100 | B120: メンテナンスボックス PJMB100（PP-100II） | D120: 純正 | E120: 3000
A121: PXMB3 | B121: メンテナンスボックス PXMB3（PX205） | D121: 純正 | E121: 1800
A122: PXMB7 | B122: メンテナンスボックス PXMB7（PX-M780F） | D122: 純正 | E122: 1800
A123: PXMB8 | B123: メンテナンスボックス PXMB8（PX-S381） | D123: 再生 | E123: 1900
A124: PXMB9 | B124: メンテナンスボックス PXMB9（PX-M791FT） | D124: 純正 | E124: 2700
A125: LPB3T24 | B125: 感光体ユニット LPB3T24（LP-2200） | C125: ブラック | D125: 再生 | E125: 6200
A126: 廃トナーボトルC220 | B126: 廃トナーボトル C220（C241,C251,C261,C301SF用）（C310・C241） | D126: 純正 | E126: 2500
A127: 廃トナーボトルC310 | B127: 廃トナーボトル C310（C310用）（C310・C241） | D127: 純正 | E127: 3000
A128: NPG-67BK | D128: 純正

Sheet 出典
A1: 出典一覧
A2: 2026-08-21 に確認。メーカー公式を優先し、公式に記載が無いものは販売店・リサイクル業者のページを使った。
A4: 出典ID | B4: 種別 | C4: 名称 | D4: URL
A5: S01 | B5: メーカー公式 | C5: リコー公式 消耗品など / RICOH P C301SF | D5: https://www.ricoh.co.jp/products/list/ricoh-p-c301sf/supply
A6: S02 | B6: メーカー公式 | C6: リコー公式 消耗品など / RICOH P 501/501M/500/500M | D6: https://www.ricoh.co.jp/products/list/ricoh-p-501-500/supply
A7: S03 | B7: メーカー公式 | C7: リコー公式 消耗品 / RICOH SP 3610 | D7: https://www.ricoh.co.jp/printer/sp/3610/support/supply.html
A8: S04 | B8: メーカー公式 | C8: リコー公式 消耗品など / IPSiO SP 4310/4300 | D8: https://www.ricoh.co.jp/products/list/ipsio-sp-4310-4300/supply
A9: S05 | B9: メーカー公式 | C9: リコー公式 消耗品 / RICOH SP 4510/4500 | D9: https://www.ricoh.co.jp/printer/sp/4510_4500/support/supply.html
A10: S06 | B10: メーカー公式 | C10: リコー公式 消耗品 / IPSiO SP C320 | D10: https://www.ricoh.co.jp/IPSiO/spc/320/support/supply.html
A11: S07 | B11: メーカー公式 | C11: リコー公式 消耗品 / RICOH SP C342/C342M/C341 | D11: https://www.ricoh.co.jp/printer/spc/342_341/support/supply.html
A12: S08 | B12: メーカー公式 | C12: リコー公式 消耗品など / RICOH SP C751/C751M/C750/C750M | D12: https://www.ricoh.co.jp/products/list/ricoh-sp-c751-c750/supply
A13: S09 | B13: メーカー公式 | C13: リコー使用説明書 消耗品一覧 / RICOH IM C6000〜C2000 | D13: https://manuals.ricoh.com/mfp/p_manual/IMC6000JPN/ja/spec/int/consumables.htm
A14: S10 | B14: メーカー公式 | C14: リコー公式 消耗品 / RICOH IM C6000/C5500/C4500/C3500/C3000/C2500 | D14: https://www.ricoh.co.jp/mfp/color/im-C6000-C5500-C4500-C3500-C3000-C2500/support/supply
A15: S11 | B15: メーカー公式 | C15: 富士フイルムBI公式 DocuPrint CP500 d 消耗品と保守サービスの価格 | D15: https://www.fujifilm.com/fb/product/printer/docuprint_cp500d/price.html
... A39: S35 | B39: 販売店・リサイクル業者 | C39: 販売店 アケボノサービス IPSiO SP 4510/SP 4500/SP 3610 対応消耗品 | D39: https://shop.akebono-sv.co.jp/html/page64.html

Sheet 凡例・前提
A1: この表の読み方と前提
A3: 対象 | B3: 端末台帳（printer_assets）62 台を、メーカー＋型番でまとめた 22 機種。台数は 2026-08-21 時点。
A5: 調査日 | B5: 2026-08-21。価格・取り扱いは変わるので、発注前に販売店へ確認すること。
A7: 価格の別 | B7: 「メーカー標準価格（税別）」＝メーカー公式ページの標準価格。「直販価格（税込）」＝メーカー直販サイトの表示価格。「実売の参考（税込）」＝販売店ページの価格例（幅がある）。「オープン価格」＝メーカーが価格を公表しておらず、販売店見積り。
A9: 印刷可能枚数 | B9: 各メーカーの公表値。A4・印字率 5% などの条件付きで、実際の枚数は使い方で変わる。ドラム・メンテナンスキットは交換の目安ページ数。
A11: 区分 | B11: トナー / インク / ドラム（感光体）/ 廃トナー（回収ボトル・容器）/ メンテナンス（キット・ボックス）/ ベルト。
A13: 照合キー | B13: システムのトナーマスタと突き合わせる品番。マスタに同じものがある場合はマスタ側の ID（例 C310H-BK）、無い場合はメーカーの品番をそのまま入れている。色違いで品番が共通のもの（C310 など）は 4 色とも同じ鍵になる。
A15: 台帳マスタ | B15: 「登録あり」＝その品番がトナーマスタにある。「未登録」＝調べた純正品がマスタに無い。「—」＝実在しない行（ドラム別売なし等）で判定していない。※マスタにあることと、機種に紐づいていることは別。紐づけは画面の「機種別トナー」で確認する。
A17: リサイクル/互換 | B17: リサイクル品（使用済みカートリッジを再生）または互換品（他社新品）の流通があるか。個別の商品を推奨するものではなく、選択肢の有無を示す。
A19: 注意（保守契約） | B19: iR-ADV C3520F/C3530F と RICOH IM C3500 は複合機で、感光体・定着などは保守契約でサービス員が交換するのが基本。一般に購入するのはトナーと廃トナー容器が中心になる。
A21: 注意（純正指定） | B21: 各メーカーとも純正品の使用を推奨しており、非純正品による不具合は保証・保守の対象外になる旨を明記している。
A23: 注意（販売終了） | B23: Ricoh の SP 系・P C301SF・IPSiO SP 4310、DocuPrint CP500 d、HL-L3230CDW などは本体が販売終了品。消耗品の供給期限があるため、在庫の持ち方は別途検討が必要。
A25: 空欄の意味 | B25: 印刷可能枚数・価格の空欄は「公表されていない／今回の調査で確認できなかった」。0 ではない。
